ValidMLInference/__init__.py
ValidMLInference/implementations.py
ValidMLInference/interfaces.py
ValidMLInference/data/__init__.py
ValidMLInference/data/remote_work_data.csv
ValidMLInference/data/topic_model_data.npz
validmlinference-1.3.0.dist-info/licenses/LICENSE
validmlinference-1.3.0.dist-info/METADATA
validmlinference-1.3.0.dist-info/WHEEL
validmlinference-1.3.0.dist-info/top_level.txt
validmlinference-1.3.0.dist-info/RECORD
