Metadata-Version: 2.4
Name: ValidMLInference
Version: 1.3.0
Summary: This package implements bias correction methods for models estimated using synthetic data
Author-email: Konrad Kurczynski <konrad.kurczynski@yale.edu>, Timothy Christensen <timothy.christensen@yale.edu>
License: MIT
Project-URL: Homepage, https://github.com/KonradKurczynski/ValidMLInference
Classifier: Programming Language :: Python :: 3
Classifier: Operating System :: OS Independent
Requires-Python: >=3.8
License-File: LICENSE
Requires-Dist: numpy
Requires-Dist: scipy
Requires-Dist: jax
Requires-Dist: jaxopt
Requires-Dist: numdifftools
Requires-Dist: patsy
Requires-Dist: pandas
Dynamic: license-file
